{
	"class" : {
		"isInput" : "8/17/2016 16:26:23",
		"isOutput" : "8/17/2016 16:26:23",
		"metaclass" : "8/17/2016 16:26:23" },
	"instance" : {
		"agreeTypesWith:" : "8/17/2016 16:26:23",
		"basicValue:" : "8/17/2016 16:26:23",
		"checkType:" : "8/17/2016 16:26:23",
		"checkTypeOfValue:" : "8/17/2016 16:26:23",
		"isCompatibleWith:" : "8/17/2016 16:26:23",
		"isInput" : "8/17/2016 16:26:23",
		"isOutput" : "8/17/2016 16:26:23",
		"meta:" : "SantiagoBragagnolo 9/7/2016 15:26",
		"noteWrittenPortOldValue:newValue:" : "8/17/2016 16:26:23",
		"privateIsCompatibleWith:" : "8/17/2016 16:26:23",
		"value" : "8/17/2016 16:26:23",
		"value:" : "8/17/2016 16:26:23" } }
