{
	"instance" : {
		"privateIsCompatibleWith:" : " 6/23/2016 17:01:07",
		"meta:" : " 6/23/2016 17:01:07",
		"basicValue:" : " 6/23/2016 17:01:07",
		"agreeTypesWith:" : " 6/23/2016 17:01:07",
		"isCompatibleWith:" : " 6/23/2016 17:01:07",
		"noteWrittenPortOldValue:newValue:" : " 6/23/2016 17:01:07",
		"value" : " 6/23/2016 17:01:07",
		"isInput" : "SantiagoBragagnolo 6/24/2016 11:44",
		"checkType:" : " 6/23/2016 17:01:07",
		"value:" : " 6/23/2016 17:01:07",
		"isOutput" : "SantiagoBragagnolo 6/24/2016 11:45",
		"checkTypeOfValue:" : " 6/23/2016 17:01:07"
	},
	"class" : {
		"isOutput" : "SantiagoBragagnolo 6/24/2016 11:44",
		"metaclass" : " 6/23/2016 17:01:07",
		"isInput" : "SantiagoBragagnolo 6/24/2016 11:44"
	}
}